moexapi/__init__.py
moexapi/bonds.py
moexapi/candles.py
moexapi/changeover.py
moexapi/dividends.py
moexapi/exchange.py
moexapi/history.py
moexapi/markets.py
moexapi/splits.py
moexapi/tickers.py
moexapi/utils.py
moexapi-1.6.36.dist-info/licenses/LICENSE
moexapi-1.6.36.dist-info/METADATA
moexapi-1.6.36.dist-info/WHEEL
moexapi-1.6.36.dist-info/top_level.txt
moexapi-1.6.36.dist-info/RECORD
