Metadata-Version: 2.4
Name: moexapi
Version: 1.6.36
Summary: Python API for MOEX ISS
Author-email: Aliaksei Rak <kventinel@gmail.com>
License: MIT License
Project-URL: Homepage, https://github.com/kventinel/moexapi
Keywords: moex
Classifier: License :: OSI Approved :: MIT License
Classifier: Programming Language :: Python
Classifier: Programming Language :: Python :: 3
Requires-Python: >=3.6
License-File: LICENSE
Requires-Dist: beautifulsoup4
Requires-Dist: requests
Requires-Dist: numpy
Dynamic: license-file
